odoo/addons/l10n_es_aeat_mod592/README.rst
odoo/addons/l10n_es_aeat_mod592/__init__.py
odoo/addons/l10n_es_aeat_mod592/__manifest__.py
odoo/addons/l10n_es_aeat_mod592/data/ir_sequence_data.xml
odoo/addons/l10n_es_aeat_mod592/docs/Contabilidad_libro.pdf
odoo/addons/l10n_es_aeat_mod592/docs/Reg. Fiscal Adquir. y Repres. (ADSIPLRA).csv
odoo/addons/l10n_es_aeat_mod592/docs/Regimen Fiscal Fabricantes (ADSIPLRF).csv
odoo/addons/l10n_es_aeat_mod592/docs/plastico_campos_impfichero.xlsx
odoo/addons/l10n_es_aeat_mod592/docs/plastico_doc_impfichero.pdf
odoo/addons/l10n_es_aeat_mod592/i18n/es.po
odoo/addons/l10n_es_aeat_mod592/i18n/l10n_es_aeat_mod592.pot
odoo/addons/l10n_es_aeat_mod592/models/__init__.py
odoo/addons/l10n_es_aeat_mod592/models/misc.py
odoo/addons/l10n_es_aeat_mod592/models/mod592.py
odoo/addons/l10n_es_aeat_mod592/models/mod592_acquirer.py
odoo/addons/l10n_es_aeat_mod592/models/mod592_line_mixin.py
odoo/addons/l10n_es_aeat_mod592/models/mod592_manufacturer.py
odoo/addons/l10n_es_aeat_mod592/models/product_product.py
odoo/addons/l10n_es_aeat_mod592/models/product_template.py
odoo/addons/l10n_es_aeat_mod592/models/res_company.py
odoo/addons/l10n_es_aeat_mod592/models/res_partner.py
odoo/addons/l10n_es_aeat_mod592/readme/CONFIGURE.md
odoo/addons/l10n_es_aeat_mod592/readme/CONTRIBUTORS.md
odoo/addons/l10n_es_aeat_mod592/readme/DESCRIPTION.md
odoo/addons/l10n_es_aeat_mod592/readme/ROADMAP.md
odoo/addons/l10n_es_aeat_mod592/readme/USAGE.md
odoo/addons/l10n_es_aeat_mod592/report/__init__.py
odoo/addons/l10n_es_aeat_mod592/report/aeat_mod592.xml
odoo/addons/l10n_es_aeat_mod592/report/common_templates.xml
odoo/addons/l10n_es_aeat_mod592/report/l10n_es_aeat_mod592_csv.py
odoo/addons/l10n_es_aeat_mod592/report/l10n_es_aeat_mod592_xlsx.py
odoo/addons/l10n_es_aeat_mod592/report/report_views.xml
odoo/addons/l10n_es_aeat_mod592/security/aeat_security.xml
odoo/addons/l10n_es_aeat_mod592/security/ir.model.access.csv
odoo/addons/l10n_es_aeat_mod592/static/description/icon.png
odoo_addon_l10n_es_aeat_mod592-17.0.1.0.3.dist-info/METADATA
odoo_addon_l10n_es_aeat_mod592-17.0.1.0.3.dist-info/WHEEL
odoo_addon_l10n_es_aeat_mod592-17.0.1.0.3.dist-info/top_level.txt
odoo_addon_l10n_es_aeat_mod592-17.0.1.0.3.dist-info/RECORD
